dfusion/__init__.py
dfusion/dfusion/__init__.py
dfusion/dfusion/common.py
dfusion/dfusion/d3pm_sampler.py
dfusion/dfusion/d3pm_trainer.py
dfusion/dfusion/d3pm_utils.py
dfusion/dfusion/ddim_sampler.py
dfusion/dfusion/ddpm_sampler.py
dfusion/dfusion/ddpm_trainer.py
dfusion/dfusion/diffusion2.py
dfusion/dfusion/diffusion_base.py
dfusion/dfusion/karras_sampler.py
dfusion/models/__init__.py
dfusion/models/kitsunetic/__init__.py
dfusion/models/kitsunetic/attention.py
dfusion/models/kitsunetic/convnextv2.py
dfusion/models/kitsunetic/modules.py
dfusion/models/kitsunetic/unet.py
dfusion/models/kitsunetic/unet2.py
dfusion/models/kitsunetic/unet_module.py
dfusion/models/kitsunetic/unext.py
dfusion/models/kitsunetic/unext2.py
dfusion/models/kitsunetic/utils.py
dfusion/utils/__init__.py
dfusion/utils/common.py
dfusion/utils/ema.py
dfusion/utils/indexing.py
dfusion/utils/scheduler.py
dfusion/utils/score/__init__.py
dfusion/utils/score/both.py
dfusion/utils/score/fid.py
dfusion/utils/score/inception.py
dfusion/utils/score/inception_score.py
dfusion-0.0.2.dist-info/METADATA
dfusion-0.0.2.dist-info/WHEEL
dfusion-0.0.2.dist-info/top_level.txt
dfusion-0.0.2.dist-info/RECORD
