Metadata-Version: 2.1
Name: dfusion
Version: 0.0.2
Summary: Easy to use library for various implementtaions of denoising diffusion models
Home-page: https://github.com/Kitsunetic/DFusion.git
Author: Kitsunetic
Author-email: jh.shim.gg@gmail.com
Classifier: Programming Language :: Python :: 3
Classifier: License :: OSI Approved :: MIT License
Classifier: Operating System :: OS Independent
Requires-Python: >=3
